stable_c_test2/__init__.py
stable_c_test2/core.py
stable_c_test2/log.py
stable_c_test2/server.py
stable_c_test2-0.1.1.dist-info/METADATA
stable_c_test2-0.1.1.dist-info/WHEEL
stable_c_test2-0.1.1.dist-info/top_level.txt
stable_c_test2-0.1.1.dist-info/RECORD
